dkist_inventory/__init__.py
dkist_inventory/asdf_generator.py
dkist_inventory/header_parsing.py
dkist_inventory/inventory.py
dkist_inventory/parameter_parsing.py
dkist_inventory/transforms.py
dkist_inventory/version.py
dkist_inventory/tests/__init__.py
dkist_inventory/tests/conftest.py
dkist_inventory/tests/test_asdf_generator.py
dkist_inventory/tests/test_header_parsing.py
dkist_inventory/tests/test_inventory.py
dkist_inventory/tests/test_parameter_parsing.py
dkist_inventory/tests/test_transforms.py
dkist_inventory-1.11.2.dist-info/licenses/licenses/LICENSE.rst
dkist_inventory-1.11.2.dist-info/METADATA
dkist_inventory-1.11.2.dist-info/WHEEL
dkist_inventory-1.11.2.dist-info/top_level.txt
dkist_inventory-1.11.2.dist-info/RECORD
