Metadata-Version: 2.4
Name: dkist-inventory
Version: 1.11.2
Summary: A shared library for dataset inventory and asdf generation.
Author: NSO / AURA
Author-email: stuart@cadair.com
License: BSD 3-Clause
Requires-Python: >=3.11
License-File: licenses/LICENSE.rst
Requires-Dist: astropy>=6.1.5
Requires-Dist: gwcs>=0.24.0
Requires-Dist: sunpy[asdf,net]>=5.0
Requires-Dist: numpy>=1.25
Requires-Dist: ndcube>=2.1
Requires-Dist: packaging
Requires-Dist: dkist-fits-specifications>=4.1.1
Requires-Dist: scipy>=1.11.0
Requires-Dist: dkist>=1.12.0
Requires-Dist: sqids>=0.5.1
Requires-Dist: pydantic>=2.0
Provides-Extra: asdf
Requires-Dist: asdf; extra == "asdf"
Provides-Extra: test
Requires-Dist: pytest; extra == "test"
Requires-Dist: pytest-doctestplus; extra == "test"
Requires-Dist: pytest-cov; extra == "test"
Requires-Dist: pytest-xdist; extra == "test"
Requires-Dist: dkist-data-simulator>=5.4.0; extra == "test"
Requires-Dist: dkist-header-validator; extra == "test"
Requires-Dist: pytest-mock; extra == "test"
Requires-Dist: filelock; extra == "test"
Provides-Extra: docs
Requires-Dist: sphinx; extra == "docs"
Requires-Dist: sphinx-automodapi; extra == "docs"
Dynamic: license-file
